redisplus.py
redisplus-0.0.1.dist-info/METADATA
redisplus-0.0.1.dist-info/WHEEL
redisplus-0.0.1.dist-info/entry_points.txt
redisplus-0.0.1.dist-info/top_level.txt
redisplus-0.0.1.dist-info/RECORD
